ratelimit/__init__.py
ratelimit/__version__.py
ratelimit/auths/__init__.py
ratelimit/auths/ip.py
ratelimit/auths/jwt.py
ratelimit/auths/session.py
ratelimit/backends/__init__.py
ratelimit/backends/base.py
ratelimit/backends/redis.py
ratelimit/backends/simple.py
ratelimit/backends/slidingredis.py
ratelimit/core.py
ratelimit/py.typed
ratelimit/rule.py
ratelimit/types.py
asgi_ratelimit-0.9.0.dist-info/LICENSE
asgi_ratelimit-0.9.0.dist-info/WHEEL
asgi_ratelimit-0.9.0.dist-info/METADATA
asgi_ratelimit-0.9.0.dist-info/RECORD
