Metadata-Version: 2.1
Name: asgi-ratelimit
Version: 0.9.0
Summary: 
Home-page: https://github.com/abersheeran/asgi-ratelimit
License: Apache-2.0
Author: abersheeran
Author-email: me@abersheeran.com
Requires-Python: >=3.6,<4.0
Classifier: License :: OSI Approved :: Apache Software License
Classifier: Programming Language :: Python :: 3
Classifier: Programming Language :: Python :: 3.10
Classifier: Programming Language :: Python :: 3.6
Classifier: Programming Language :: Python :: 3.7
Classifier: Programming Language :: Python :: 3.8
Classifier: Programming Language :: Python :: 3.9
Provides-Extra: full
Provides-Extra: jwt
Provides-Extra: redis
Requires-Dist: dataclasses (>=0.6,<0.7); python_version >= "3.6" and python_version < "3.7"
Requires-Dist: pyjwt (>=1.7.1,<2.0.0); extra == "jwt" or extra == "full"
Requires-Dist: redis (>=4.2.0rc2); extra == "redis" or extra == "full"
Project-URL: Repository, https://github.com/abersheeran/asgi-ratelimit
